{
  "description": "A checkbox component for use in forms.",
  "displayName": "Checkbox",
  "methods": [
    {
      "name": "onChange",
      "docblock": null,
      "modifiers": [],
      "params": [
        {
          "name": "e",
          "type": null
        }
      ],
      "returns": null
    }
  ],
  "props": {
    "classes": {
      "flowType": {
        "name": "Object"
      },
      "required": true,
      "description": ""
    },
    "className": {
      "flowType": {
        "name": "string"
      },
      "required": true,
      "description": "className to be passed to the component."
    },
    "field": {
      "flowType": {
        "name": "Object"
      },
      "required": true,
      "description": ""
    },
    "form": {
      "flowType": {
        "name": "Object"
      },
      "required": true,
      "description": ""
    },
    "options": {
      "flowType": {
        "name": "Array",
        "elements": [
          {
            "name": "signature",
            "type": "object",
            "raw": "{ label: string, value: string }",
            "signature": {
              "properties": [
                {
                  "key": "label",
                  "value": {
                    "name": "string",
                    "required": true
                  }
                },
                {
                  "key": "value",
                  "value": {
                    "name": "string",
                    "required": true
                  }
                }
              ]
            }
          }
        ],
        "raw": "Array<{ label: string, value: string }>"
      },
      "required": true,
      "description": ""
    },
    "label": {
      "flowType": {
        "name": "string"
      },
      "required": true,
      "description": "Text input for the label of the checkbox."
    },
    "theme": {
      "flowType": {
        "name": "Object"
      },
      "required": true,
      "description": ""
    }
  }
}
